snowctl/__init__.py
snowctl/arguments.py
snowctl/config.py
snowctl/connect.py
snowctl/copy.py
snowctl/logger.py
snowctl/snowctl.py
snowctl/utils.py
snowctl-1.0.9.dist-info/LICENSE
snowctl-1.0.9.dist-info/METADATA
snowctl-1.0.9.dist-info/WHEEL
snowctl-1.0.9.dist-info/entry_points.txt
snowctl-1.0.9.dist-info/top_level.txt
snowctl-1.0.9.dist-info/RECORD
