Metadata-Version: 2.1
Name: snowctl
Version: 1.0.9
Summary: A cli tool for automating tasks in Snowflake Database
Home-page: https://github.com/Rouhija/snowflake-cli
Author: Sami Rouhe
Author-email: rouhesami@gmail.com
License: UNKNOWN
Platform: UNKNOWN
Classifier: Programming Language :: Python :: 3
Classifier: License :: OSI Approved :: MIT License
Classifier: Operating System :: OS Independent
Requires-Dist: snowflake-connector-python (==2.2.4)
Requires-Dist: snowflake-sqlalchemy (==1.2.3)
